{"m.klikbca.com":{"/":{"JSESSIONID":{"key":"JSESSIONID","value":"JtfyX0JpGYZ6rbJjptG4Hm2j0k6pR9KhzhhNS63CKzMc36pGLpgz!1667468522","domain":"m.klikbca.com","path":"/","secure":true,"httpOnly":true,"hostOnly":true,"creation":"2016-06-29T23:09:09.800Z","lastAccessed":"2016-06-29T23:09:10.427Z"},"Cookie-NS-Mklikbca":{"key":"Cookie-NS-Mklikbca","value":"ffffffff090834f245525d5f4f58455e445a4a42378b","domain":"m.klikbca.com","path":"/","secure":true,"httpOnly":true,"hostOnly":true,"creation":"2016-06-29T23:09:09.803Z","lastAccessed":"2016-06-29T23:09:10.344Z"}}}}